daolite/__init__.py
daolite/common.py
daolite/component.py
daolite/config.py
daolite/compute/__init__.py
daolite/compute/base_resources.py
daolite/compute/compute_resources.py
daolite/compute/hardware/__init__.py
daolite/compute/hardware/amd_epyc_7402.yaml
daolite/compute/hardware/amd_epyc_7542.yaml
daolite/compute/hardware/amd_epyc_7543.yaml
daolite/compute/hardware/amd_epyc_7601.yaml
daolite/compute/hardware/amd_epyc_7713.yaml
daolite/compute/hardware/amd_epyc_7763.yaml
daolite/compute/hardware/amd_epyc_9654.yaml
daolite/compute/hardware/amd_fx_8350.yaml
daolite/compute/hardware/amd_mi300x.yaml
daolite/compute/hardware/amd_radeon_rx580.yaml
daolite/compute/hardware/amd_radeon_vega64.yaml
daolite/compute/hardware/amd_ryzen_1800x.yaml
daolite/compute/hardware/amd_ryzen_3700x.yaml
daolite/compute/hardware/amd_ryzen_5950x.yaml
daolite/compute/hardware/amd_ryzen_7950x.yaml
daolite/compute/hardware/intel_core_i7_4770k.yaml
daolite/compute/hardware/intel_core_i7_7700k.yaml
daolite/compute/hardware/intel_core_i9_12900k.yaml
daolite/compute/hardware/intel_core_i9_9900k.yaml
daolite/compute/hardware/intel_xeon_8462.yaml
daolite/compute/hardware/intel_xeon_8480.yaml
daolite/compute/hardware/intel_xeon_e5_2690v4.yaml
daolite/compute/hardware/nvidia_a100_80gb.yaml
daolite/compute/hardware/nvidia_gtx_1080ti.yaml
daolite/compute/hardware/nvidia_gtx_980.yaml
daolite/compute/hardware/nvidia_h100_80gb.yaml
daolite/compute/hardware/nvidia_rtx_2080ti.yaml
daolite/compute/hardware/nvidia_rtx_4090.yaml
daolite/compute/hardware/nvidia_tesla_k80.yaml
daolite/compute/hardware/nvidia_tesla_p100.yaml
daolite/gui/__init__.py
daolite/gui/centroid_agenda_tool.py
daolite/gui/pipeline_designer.py
daolite/gui/designer/__init__.py
daolite/gui/designer/code_generator.py
daolite/gui/designer/component_block.py
daolite/gui/designer/component_container.py
daolite/gui/designer/connection.py
daolite/gui/designer/connection_manager.py
daolite/gui/designer/data_transfer.py
daolite/gui/designer/file_io.py
daolite-0.1.1.dist-info/licenses/LICENSE
daolite-0.1.1.dist-info/METADATA
daolite-0.1.1.dist-info/WHEEL
daolite-0.1.1.dist-info/entry_points.txt
daolite-0.1.1.dist-info/top_level.txt
daolite-0.1.1.dist-info/RECORD
