Metadata-Version: 2.4
Name: daolite
Version: 0.1.1
Summary: A Python package for estimating latency in Adaptive Optics Real-time Control Systems
Author-email: David Barr <dave@davetbarr.com>
Maintainer-email: David Barr <dave@davetbarr.com>
License-Expression: GPL-3.0-or-later
Project-URL: Homepage, https://github.com/davetbarr/daolite
Project-URL: Documentation, https://daolite.readthedocs.io
Project-URL: Repository, https://github.com/davetbarr/daolite
Project-URL: Bug Tracker, https://github.com/davetbarr/daolite/issues
Keywords: adaptive optics,latency,astronomy,real-time control,AO,RTC
Classifier: Development Status :: 3 - Alpha
Classifier: Intended Audience :: Science/Research
Classifier: Topic :: Scientific/Engineering :: Astronomy
Classifier: Topic :: Scientific/Engineering :: Physics
Classifier: Programming Language :: Python :: 3
Classifier: Programming Language :: Python :: 3.8
Classifier: Programming Language :: Python :: 3.9
Classifier: Programming Language :: Python :: 3.10
Classifier: Programming Language :: Python :: 3.11
Classifier: Operating System :: OS Independent
Requires-Python: >=3.8
License-File: LICENSE
Requires-Dist: numpy>=1.20.0
Requires-Dist: matplotlib>=3.4.0
Requires-Dist: pyyaml>=5.4.0
Requires-Dist: cycler>=0.10.0
Requires-Dist: regex>=2021.8.3
Requires-Dist: pyqt5>=5.15.0
Provides-Extra: dev
Requires-Dist: pytest; extra == "dev"
Requires-Dist: pytest-cov; extra == "dev"
Requires-Dist: sphinx; extra == "dev"
Requires-Dist: sphinx-rtd-theme; extra == "dev"
Requires-Dist: black; extra == "dev"
Requires-Dist: ruff; extra == "dev"
Requires-Dist: isort; extra == "dev"
Requires-Dist: pre-commit; extra == "dev"
Provides-Extra: docs
Requires-Dist: sphinx; extra == "docs"
Requires-Dist: sphinx-rtd-theme; extra == "docs"
Provides-Extra: test
Requires-Dist: pytest; extra == "test"
Requires-Dist: pytest-cov; extra == "test"
Dynamic: license-file
